demo/demo/__init__.py
demo/demo/models.py
demo/demo/migrations/0001_initial.py
demo/demo/migrations/__init__.py
populous/__init__.py
populous/__main__.py
populous/bloom.py
populous/blueprint.py
populous/buffer.py
populous/cli.py
populous/compat.py
populous/exceptions.py
populous/factory.py
populous/item.py
populous/jinja.py
populous/loader.py
populous/vars.py
populous/backends/__init__.py
populous/backends/base.py
populous/backends/postgres.py
populous/django/__init__.py
populous/django/apps.py
populous/django/management/__init__.py
populous/django/management/commands/__init__.py
populous/django/management/commands/populous.py
populous/generators/__init__.py
populous/generators/base.py
populous/generators/boolean.py
populous/generators/choices.py
populous/generators/date.py
populous/generators/email.py
populous/generators/integer.py
populous/generators/ip.py
populous/generators/name.py
populous/generators/select.py
populous/generators/store.py
populous/generators/text.py
populous/generators/url.py
populous/generators/uuid.py
populous/generators/value.py
populous/generators/yaml.py
populous-0.6.0.dist-info/LICENSE
populous-0.6.0.dist-info/METADATA
populous-0.6.0.dist-info/WHEEL
populous-0.6.0.dist-info/entry_points.txt
populous-0.6.0.dist-info/top_level.txt
populous-0.6.0.dist-info/RECORD
