Metadata-Version: 2.1
Name: populous
Version: 0.6.0
Summary: Populate your database with god-like powers
Home-page: http://github.com/peopledoc/populous
Author: PeopleDoc
Author-email: yannick.peroux@people-doc.com
License: MIT
Keywords: populous populate database
Platform: UNKNOWN
Classifier: Development Status :: 3 - Alpha
Classifier: License :: OSI Approved :: MIT License
Classifier: Operating System :: POSIX
Classifier: Programming Language :: Python :: 3.7
Classifier: Programming Language :: Python :: 3.8
Classifier: Programming Language :: Python :: 3.9
Classifier: Topic :: Utilities
License-File: LICENSE
Requires-Dist: click
Requires-Dist: click-log (>=0.2.0)
Requires-Dist: cached-property
Requires-Dist: dateutils
Requires-Dist: Faker
Requires-Dist: Jinja2
Requires-Dist: PyYAML
Requires-Dist: peloton-bloomfilters-py3
Provides-Extra: tests
Requires-Dist: tox ; extra == 'tests'
Requires-Dist: pytest ; extra == 'tests'
Requires-Dist: pytest-mock ; extra == 'tests'
Requires-Dist: flake8 ; extra == 'tests'
Requires-Dist: isort ; extra == 'tests'
Requires-Dist: black ; extra == 'tests'
